[
    {
        "name": "Extension Cheats",
        "type": "category",
        "url": "/extension-cheats",
        "items": [
            {
                "name": "Page Extension",
                "type": "page",
                "url": "/page-extension"
            }
        ]
    }, 
    {
        "name": "Examples",
        "type": "category",
        "url": "/examples",
        "items": [
            {
                "name": "Hello World Example",
                "type": "page",
                "url": "/hello-world"
            },
            {
                "name": "Realtime Example",
                "type": "page",
                "url": "/realtime"
            },
            {
                "name": "Widget Events",
                "type": "page",
                "url": "/widget-events"
            }
        ]
    },
    {
        "name": "Want to contribute?",
        "type": "page",
        "url": "/contributing",
        "items": []
    }
]
